csp/__init__.py
csp/aip/Detection.py
csp/aip/Kg.py
csp/aip/Ocr.py
csp/aip/PdfCheck.py
csp/aip/Translate.py
csp/aip/Uiepipe.py
csp/aip/Unst2st.py
csp/aip/__init__.py
csp/aip/common/__init__.py
csp/aip/common/docker_base.py
csp/aip/common/http_client.py
csp/command/__init__.py
csp/command/cli.py
csp/command/cli_all.py
csp/common/__init__.py
csp/common/config.py
csp/common/docker_server.py
csp/common/utils.py
csp/common/config/docker_dict.yaml
csp/common/config/interface.yaml
csp/common/config/user_config.yaml
csp/dataset/__init__.py
csp/dataset/dataset_cli.py
csp/dataset/dataset_server.py
csp/datatool/APIs.py
csp/datatool/__init__.py
csp/datatool/aug.py
csp/datatool/check.py
csp/datatool/datatool_cli.py
csp/datatool/eda.py
csp/datatool/eva.py
csp/datatool/merge.py
csp/datatool/split.py
csp/datatool/transform.py
csp/datatool/utils.py
csp/datatool/dataset/__init__.py
csp/datatool/dataset/dataset.py
csp/datatool/image_classify/__init__.py
csp/datatool/image_classify/aug.py
csp/datatool/image_classify/check.py
csp/datatool/image_classify/eda.py
csp/datatool/image_classify/eva.py
csp/datatool/image_classify/split.py
csp/datatool/image_classify/transform.py
csp/datatool/image_classify/utils.py
csp/datatool/image_detection/__init__.py
csp/datatool/image_detection/aug.py
csp/datatool/image_detection/bg_changed.py
csp/datatool/image_detection/check.py
csp/datatool/image_detection/eda.py
csp/datatool/image_detection/eva.py
csp/datatool/image_detection/eva_badcase.py
csp/datatool/image_detection/simhei.ttf
csp/datatool/image_detection/split.py
csp/datatool/image_detection/transform.py
csp/datatool/image_detection/utils.py
csp/datatool/image_detection/voc_xml.py
csp/datatool/text_classify/__init__.py
csp/datatool/text_classify/check.py
csp/datatool/text_classify/eda.py
csp/datatool/text_classify/eva.py
csp/datatool/text_classify/split.py
csp/datatool/text_classify/utils.py
csp/datatool/text_entity/__init__.py
csp/datatool/text_entity/check.py
csp_cli-1.3.3.dist-info/METADATA
csp_cli-1.3.3.dist-info/WHEEL
csp_cli-1.3.3.dist-info/entry_points.txt
csp_cli-1.3.3.dist-info/top_level.txt
csp_cli-1.3.3.dist-info/RECORD
